{
	"info": {
		"_postman_id": "31190e0e-659b-42e3-ade3-046dca994f49",
		"name": "Meal Sharing",
		"schema": "https://schema.getpostman.com/json/collection/v2.1.0/collection.json",
		"_exporter_id": "38149924"
	},
	"item": [
		{
			"name": "New Folder",
			"item": [
				{
					"name": "https://raw.githubusercontent.com/Bayram89/Bayram89.github.io/refs/heads/main/recipes.json",
					"request": {
						"method": "GET",
						"header": [],
						"url": {
							"raw": "https://raw.githubusercontent.com/Bayram89/Bayram89.github.io/refs/heads/main/recipes.json",
							"protocol": "https",
							"host": [
								"raw",
								"githubusercontent",
								"com"
							],
							"path": [
								"Bayram89",
								"Bayram89.github.io",
								"refs",
								"heads",
								"main",
								"recipes.json"
							]
						}
					},
					"response": []
				},
				{
					"name": "http://localhost:3000/api/meals/1\n",
					"request": {
						"method": "GET",
						"header": [],
						"url": {
							"raw": "http://localhost:3000/api/meals/1\n",
							"protocol": "http",
							"host": [
								"localhost"
							],
							"port": "3000",
							"path": [
								"api",
								"meals",
								"1\n"
							]
						}
					},
					"response": []
				},
				{
					"name": "http://localhost:3000/api/meals/3\n",
					"request": {
						"method": "DELETE",
						"header": [],
						"body": {
							"mode": "raw",
							"raw": "{ \"message\": \"Meal deleted\" }",
							"options": {
								"raw": {
									"language": "json"
								}
							}
						},
						"url": {
							"raw": "http://localhost:3000/api/meals/3\n",
							"protocol": "http",
							"host": [
								"localhost"
							],
							"port": "3000",
							"path": [
								"api",
								"meals",
								"3\n"
							]
						}
					},
					"response": []
				},
				{
					"name": "http://localhost:3000/api/meals/1",
					"request": {
						"method": "PUT",
						"header": [],
						"body": {
							"mode": "raw",
							"raw": "{\n  \"price\": 25,\n  \"location\": \"Updated location\"\n}",
							"options": {
								"raw": {
									"language": "json"
								}
							}
						},
						"url": {
							"raw": "http://localhost:3000/api/meals/1",
							"protocol": "http",
							"host": [
								"localhost"
							],
							"port": "3000",
							"path": [
								"api",
								"meals",
								"1"
							]
						}
					},
					"response": []
				},
				{
					"name": "http://localhost:3000/api/meals",
					"request": {
						"method": "POST",
						"header": [],
						"body": {
							"mode": "raw",
							"raw": "{\n  \"title\": \"Baghali Polo\",\n  \"description\": \"Rice with dill and beans served with lamb\",\n  \"location\": \"Rasht - Local Restaurant\",\n  \"when\": \"2025-10-06 18:00:00\",\n  \"max_reservations\": 20,\n  \"price\": 19,\n  \"created_date\": \"2025-09-24 22:00:00\"\n}",
							"options": {
								"raw": {
									"language": "json"
								}
							}
						},
						"url": {
							"raw": "http://localhost:3000/api/meals",
							"protocol": "http",
							"host": [
								"localhost"
							],
							"port": "3000",
							"path": [
								"api",
								"meals"
							]
						}
					},
					"response": []
				},
				{
					"name": "http://localhost:3000/api/reservations",
					"request": {
						"method": "GET",
						"header": [],
						"url": {
							"raw": "http://localhost:3000/api/reservations",
							"protocol": "http",
							"host": [
								"localhost"
							],
							"port": "3000",
							"path": [
								"api",
								"reservations"
							]
						}
					},
					"response": []
				},
				{
					"name": " http://localhost:3000/api/reservations",
					"request": {
						"method": "PUT",
						"header": [],
						"body": {
							"mode": "raw",
							"raw": "{\n  \"number_of_guests\": 67,\n  \"meal_id\": 1,\n  \"created_date\": \"2025-09-30 12:00:00\",\n  \"contact_name\": \"Ali Sharifi\",\n  \"contact_email\": \"ali.sharifi@example.com\",\n  \"contact_phone_number\": \"09121234567\"\n}",
							"options": {
								"raw": {
									"language": "json"
								}
							}
						},
						"url": {
							"raw": "http://localhost:3000/api/reservations/6",
							"protocol": "http",
							"host": [
								"localhost"
							],
							"port": "3000",
							"path": [
								"api",
								"reservations",
								"6"
							]
						}
					},
					"response": []
				},
				{
					"name": " http://localhost:3000/api/reservations/6",
					"request": {
						"method": "DELETE",
						"header": [],
						"url": {
							"raw": "http://localhost:3000/api/reservations/6",
							"protocol": "http",
							"host": [
								"localhost"
							],
							"port": "3000",
							"path": [
								"api",
								"reservations",
								"6"
							]
						}
					},
					"response": []
				}
			]
		}
	]
}